gitmiller/__init__.py
gitmiller/command_line.py
gitmiller-0.1.5.dist-info/METADATA
gitmiller-0.1.5.dist-info/WHEEL
gitmiller-0.1.5.dist-info/entry_points.txt
gitmiller-0.1.5.dist-info/top_level.txt
gitmiller-0.1.5.dist-info/RECORD
