Metadata-Version: 2.1
Name: gitmiller
Version: 0.1.5
Summary: A tool to run a Jupyter Notebook from a (partial) Github repository.
Home-page: https://github.com/UtrechtUniversity/GitMiller
Author: Casper Kaandorp
Author-email: c.s.kaandorp@uu.nl
License: UNKNOWN
Platform: UNKNOWN
Classifier: Programming Language :: Python :: 3
Requires-Python: >=3.6
Requires-Dist: jupyterlab (>=1.2.6)
Requires-Dist: nbformat (>=5.1.2)
Requires-Dist: matlab-kernel
Requires-Dist: papermill
Requires-Dist: PyGithub (>=1.54.1)
Requires-Dist: pyyaml
Requires-Dist: tqdm
